<doctrine-mapping xmlns="https://doctrine-project.org/schemas/orm/doctrine-mapping"
                  xmlns:xsi="https://www.w3.org/2001/XMLSchema-instance"
                  xsi:schemaLocation="https://doctrine-project.org/schemas/orm/doctrine-mapping
                          https://www.doctrine-project.org/schemas/orm/doctrine-mapping.xsd">
    <entity name="ChameleonSystem\CoreBundle\Entity\ShopSearchCache" table="shop_search_cache">




        <id name="id" type="string" length="36" column="id" unique="true" />
        <field name="cmsident" type="integer" column="cmsident" unique="true">
            <generator strategy="AUTO"/>
        </field>
            <many-to-one field="shop" target-entity="\ChameleonSystem\CoreBundle\Entity\Shop" inversed-by="shopSearchCacheCollection" >
    <join-column name="shop_id" referenced-column-name="id" />
</many-to-one>
            <field name="searchkey" type="string" column="searchkey" length="32" nullable="false"  />
            <one-to-many field="shopSearchCacheItemCollection" target-entity="\ChameleonSystem\CoreBundle\Entity\ShopSearchCacheItem" mapped-by="shopSearchCache" orphan-removal="true">
    <cascade-persist/>
</one-to-many>

            <field name="numberOfRecordsFound" type="string" column="number_of_records_found" length="255" nullable="false"  />
    </entity>

</doctrine-mapping>